minka/__init__.py
minka/minka.py
minka_johann_haselberger-1.0.1.dist-info/METADATA
minka_johann_haselberger-1.0.1.dist-info/WHEEL
minka_johann_haselberger-1.0.1.dist-info/top_level.txt
minka_johann_haselberger-1.0.1.dist-info/RECORD
