Metadata-Version: 2.1
Name: minka-johann-haselberger
Version: 1.0.1
Summary: The minka package
Home-page: https://github.com/
Author: Johann Haselberger
Author-email: johann.haselberger@hs-kempten.de
License: UNKNOWN
Platform: UNKNOWN
Classifier: Programming Language :: Python :: 3
Classifier: License :: OSI Approved :: MIT License
Classifier: Operating System :: OS Independent
Requires-Python: >=3.6
Requires-Dist: matplotlib
Requires-Dist: numpy
Requires-Dist: PyYAML (==4.2b4)
Requires-Dist: optuna
Requires-Dist: sacred
Requires-Dist: python-telegram-bot
Requires-Dist: dnspython
Requires-Dist: loguru
Requires-Dist: wandb
Requires-Dist: pymongo
Requires-Dist: graphql-core (==2.1)
